LICENSE.txt
MANIFEST.in
README.md
setup.cfg
setup.py
lcopt/__init__.py
lcopt/_analysis_old.py
lcopt/analysis.py
lcopt/bw2_export.py
lcopt/bw2_parameter_utils.py
lcopt/bw2query.py
lcopt/interact.py
lcopt/io.py
lcopt/ipython_interactive.py
lcopt/model.py
lcopt/parameter_interpreter.py
lcopt/parameter_scan.py
lcopt.egg-info/PKG-INFO
lcopt.egg-info/SOURCES.txt
lcopt.egg-info/dependency_links.txt
lcopt.egg-info/top_level.txt
lcopt/assets/biosphere3.pickle
lcopt/assets/ecoinvent3_3.pickle
lcopt/static/THIS IS SYMLINKED TO THE NOTEBOOK TEST PATH
lcopt/static/css/analysis (James Joyce's conflicted copy 2017-03-15).css
lcopt/static/css/analysis.css
lcopt/static/css/d3testing.css
lcopt/static/css/function_box.css
lcopt/static/css/parameter_table.css
lcopt/static/css/sandbox (James Joyce's conflicted copy 2017-03-15).css
lcopt/static/css/sandbox.css
lcopt/static/css/status.css
lcopt/static/css/style.css
lcopt/static/css/testing.css
lcopt/static/css/treetest (James Joyce's conflicted copy 2017-03-15).css
lcopt/static/css/treetest.css
lcopt/static/css/typeahead.css
lcopt/static/css/cdn_cache/Muli-Regular.ttf
lcopt/static/css/cdn_cache/bootstrap-dialog.min.css
lcopt/static/css/cdn_cache/bootstrap-select.min.css
lcopt/static/css/cdn_cache/bootstrap.min.css
lcopt/static/css/cdn_cache/font-awesome.min.css
lcopt/static/css/cdn_cache/jquery-ui.css
lcopt/static/css/cdn_cache/jquery.tagsinput.min.css
lcopt/static/css/cdn_cache/material-icons.css
lcopt/static/css/cdn_cache/material-icons.woff2
lcopt/static/css/cdn_cache/selectize.bootstrap3.css
lcopt/static/css/cdn_cache/selectize.css
lcopt/static/css/cdn_cache/selectize.default.css
lcopt/static/css/cdn_cache/images/ui-icons_222222_256x240.png
lcopt/static/css/cdn_cache/images/ui-icons_555555_256x240.png
lcopt/static/css/cdn_cache/images/ui-icons_777620_256x240.png
lcopt/static/css/cdn_cache/images/ui-icons_777777_256x240.png
lcopt/static/css/cdn_cache/images/ui-icons_cc0000_256x240.png
lcopt/static/css/cdn_cache/images/ui-icons_ffffff_256x240.png
lcopt/static/data/datafile.json
lcopt/static/data/test_results.json
