Metadata-Version: 1.1
Name: lcopt
Version: 0.2.1
Summary: Life cycle optimisation module
Home-page: https://github.com/pjamesjoyce/lcopt/
Author: P. James Joyce
Author-email: pjamesjoyce@gmail.com
License: Copyright (c) 2016, P. James Joyce
